algorithmia_api_client/__init__.py
algorithmia_api_client/api_client.py
algorithmia_api_client/configuration.py
algorithmia_api_client/exceptions.py
algorithmia_api_client/rest.py
algorithmia_api_client/api/__init__.py
algorithmia_api_client/api/admin_api.py
algorithmia_api_client/api/algorithms_api.py
algorithmia_api_client/api/auth_api.py
algorithmia_api_client/api/builds_api.py
algorithmia_api_client/api/connections_api.py
algorithmia_api_client/api/connectors_api.py
algorithmia_api_client/api/data_api.py
algorithmia_api_client/api/eventlisteners_api.py
algorithmia_api_client/api/frontend_api.py
algorithmia_api_client/api/invites_api.py
algorithmia_api_client/api/notifications_api.py
algorithmia_api_client/api/organizations_api.py
algorithmia_api_client/api/registries_api.py
algorithmia_api_client/api/reservations_api.py
algorithmia_api_client/api/scm_api.py
algorithmia_api_client/api/secrets_api.py
algorithmia_api_client/api/style_api.py
algorithmia_api_client/api/usage_api.py
algorithmia_api_client/api/users_api.py
algorithmia_api_client/models/__init__.py
algorithmia_api_client/models/algorithm_asynchronous_invocation_result.py
algorithmia_api_client/models/algorithm_callability.py
algorithmia_api_client/models/algorithm_error_entry.py
algorithmia_api_client/models/algorithm_host_username.py
algorithmia_api_client/models/algorithm_host_username_updates.py
algorithmia_api_client/models/algorithm_invocation_result.py
algorithmia_api_client/models/algorithm_secret_create_request.py
algorithmia_api_client/models/algorithm_secret_edit_request.py
algorithmia_api_client/models/algorithm_secret_list.py
algorithmia_api_client/models/algorithm_secret_result.py
algorithmia_api_client/models/algorithm_synchronous_invocation_result.py
algorithmia_api_client/models/algorithm_synchronous_invocation_result_error.py
algorithmia_api_client/models/algorithm_synchronous_invocation_result_metadata.py
algorithmia_api_client/models/algorithm_synchronous_invocation_result_one_of.py
algorithmia_api_client-1.5.5.dist-info/METADATA
algorithmia_api_client-1.5.5.dist-info/WHEEL
algorithmia_api_client-1.5.5.dist-info/top_level.txt
algorithmia_api_client-1.5.5.dist-info/RECORD
