Metadata-Version: 2.1
Name: algorithmia-api-client
Version: 1.5.5
Summary: Algorithmia Management APIs
Home-page: UNKNOWN
Author: Algorithmia Support Team
Author-email: support@algorithmia.com
License: UNKNOWN
Keywords: OpenAPI,OpenAPI-Generator,Algorithmia Management APIs
Platform: UNKNOWN
Requires-Dist: urllib3 (>=1.15)
Requires-Dist: six (>=1.10)
Requires-Dist: certifi
Requires-Dist: python-dateutil
